{
  "index": 479,
  "name": "Rotom",
  "image_url": "http://serebii.net/xy/pokemon/479.png",
  "types": [

  ],
  "evolutions": [

  ],
  "moves": [
    {
      "level": "—",
      "name": "Discharge",
      "type": "electric",
      "category": "special",
      "attack": "80",
      "accuracy": "100",
      "pp": "15",
      "effect_percent": "30",
      "description": "A flare of electricity is loosed to strike the area around the user. It may also cause paralysis."
    },
    {
      "level": "—",
      "name": "Charge",
      "type": "electric",
      "category": "other",
      "attack": "--",
      "accuracy": "--",
      "pp": "20",
      "effect_percent": "--",
      "description": "The user boosts the power of the Electric move it uses on the next turn. It also raises the user's Sp. Def stat."
    },
    {
      "level": "—",
      "name": "Trick",
      "type": "psychic",
      "category": "other",
      "attack": "--",
      "accuracy": "100",
      "pp": "10",
      "effect_percent": "--",
      "description": "The user catches the target off guard and swaps its held item with its own."
    },
    {
      "level": "—",
      "name": "Astonish",
      "type": "ghost",
      "category": "physical",
      "attack": "30",
      "accuracy": "100",
      "pp": "15",
      "effect_percent": "30",
      "description": "The user attacks the target while shouting in a startling fashion. It may also make the target flinch."
    },
    {
      "level": "—",
      "name": "Thunder Wave",
      "type": "electric",
      "category": "other",
      "attack": "--",
      "accuracy": "100",
      "pp": "20",
      "effect_percent": "--",
      "description": "A weak electric charge is launched at the target. It causes paralysis if it hits."
    },
    {
      "level": "—",
      "name": "Thunder Shock",
      "type": "electric",
      "category": "special",
      "attack": "40",
      "accuracy": "100",
      "pp": "30",
      "effect_percent": "10",
      "description": "A jolt of electricity is hurled at the target to inflict damage. It may also leave the target with paralysis."
    },
    {
      "level": "—",
      "name": "Confuse Ray",
      "type": "ghost",
      "category": "other",
      "attack": "--",
      "accuracy": "100",
      "pp": "10",
      "effect_percent": "--",
      "description": "The target is exposed to a sinister ray that triggers confusion."
    },
    {
      "level": "8",
      "name": "Uproar",
      "type": "normal",
      "category": "special",
      "attack": "90",
      "accuracy": "100",
      "pp": "10",
      "effect_percent": "--",
      "description": "The user attacks in an uproar for three turns. Over that time, no one can fall asleep."
    },
    {
      "level": "15",
      "name": "Double Team",
      "type": "normal",
      "category": "other",
      "attack": "--",
      "accuracy": "--",
      "pp": "15",
      "effect_percent": "--",
      "description": "By moving rapidly, the user makes illusory copies of itself to raise its evasiveness."
    },
    {
      "level": "22",
      "name": "Shock Wave",
      "type": "electric",
      "category": "special",
      "attack": "60",
      "accuracy": "--",
      "pp": "20",
      "effect_percent": "--",
      "description": "The user strikes the target with a quick jolt of electricity. This attack cannot be evaded."
    },
    {
      "level": "29",
      "name": "Ominous Wind",
      "type": "ghost",
      "category": "special",
      "attack": "60",
      "accuracy": "100",
      "pp": "5",
      "effect_percent": "10",
      "description": "The user blasts the target with a gust of repulsive wind. It may also raise all the user's stats at once."
    },
    {
      "level": "36",
      "name": "Substitute",
      "type": "normal",
      "category": "other",
      "attack": "--",
      "accuracy": "--",
      "pp": "10",
      "effect_percent": "--",
      "description": "The user makes a copy of itself using some of its HP. The copy serves as the user's decoy."
    },
    {
      "level": "43",
      "name": "Electro Ball",
      "type": "electric",
      "category": "special",
      "attack": "??",
      "accuracy": "100",
      "pp": "10",
      "effect_percent": "--",
      "description": "The user hurls an electric orb at the target. The faster the user is than the target, the greater the damage."
    },
    {
      "level": "50",
      "name": "Hex",
      "type": "ghost",
      "category": "special",
      "attack": "65",
      "accuracy": "100",
      "pp": "10",
      "effect_percent": "--",
      "description": "This relentless attack does massive damage to a target affected by status problems."
    },
    {
      "level": "57",
      "name": "Charge",
      "type": "electric",
      "category": "other",
      "attack": "--",
      "accuracy": "--",
      "pp": "20",
      "effect_percent": "--",
      "description": "The user boosts the power of the Electric move it uses on the next turn. It also raises the user's Sp. Def stat."
    },
    {
      "level": "64",
      "name": "Discharge",
      "type": "electric",
      "category": "special",
      "attack": "80",
      "accuracy": "100",
      "pp": "15",
      "effect_percent": "30",
      "description": "A flare of electricity is loosed to strike the area around the user. It may also cause paralysis."
    }
  ]
}